{
  "_id": "2Jaz98WiQMNnqKCD",
  "name": "Monitor Lizard Support Benefit",
  "type": "action",
  "img": "systems/pf2e/icons/actions/OneAction.webp",
  "effects": [],
  "folder": null,
  "sort": 3100000,
  "flags": {
    "core": {
      "sourceId": "Compendium.pf2e-animal-companions.AC-Support.Item.2Jaz98WiQMNnqKCD"
    }
  },
  "system": {
    "description": {
      "gm": "",
      "value": "<p>The monitor lizard distracts an adjacent opponent with snapping jaws and rapid movements. Until the start of your next turn, if your Strike damages a foe, any time the foe attempts an action with the manipulate trait until the end of your next turn, it must attempt a @Check[flat|dc:5|showDC:all]. On a failure, the action is disrupted.</p>"
    },
    "rules": [],
    "slug": "monitor-lizard-support-benefit",
    "_migration": {
      "version": null,
      "lastMigration": null
    },
    "traits": {
      "otherTags": [],
      "value": [],
      "rarity": "common"
    },
    "publication": {
      "title": "",
      "authors": "",
      "license": "OGL",
      "remaster": false
    },
    "actionType": {
      "value": "action"
    },
    "category": "offensive",
    "actions": {
      "value": 1
    },
    "deathNote": false,
    "source": {
      "value": ""
    },
    "schema": {
      "version": 0.854,
      "lastMigration": {
        "datetime": "2023-06-27T14:18:03.611-04:00",
        "version": {
          "schema": 0.845,
          "foundry": "11.307",
          "system": "5.3.1"
        }
      }
    },
    "requirements": {
      "value": ""
    },
    "trigger": {
      "value": ""
    },
    "weapon": {
      "value": ""
    }
  },
  "ownership": {
    "default": 0,
    "WG8TaxGEQOxXBO1S": 3
  },
  "_stats": {
    "systemId": "pf2e",
    "systemVersion": "6.7.2",
    "coreVersion": "12.331",
    "compendiumSource": "Compendium.pf2e-animal-companions.AC-Support.Item.2Jaz98WiQMNnqKCD",
    "duplicateSource": null
  },
  "_key": "!items!2Jaz98WiQMNnqKCD"
}
