{
  "name": "Shotalashu Support Benefit",
  "type": "action",
  "effects": [],
  "system": {
    "description": {
      "gm": "",
      "value": "<p>The shotalashu telepathically assails your enemies when you create an opening. Until the start of your next turn, each time you hit a creature in the shotalashu's reach with a Strike, the creature takes @Damage[1d6[mental]] damage from the shotalashu. If your shotalashu is nimble or savage, the mental damage increases to @Damage[2d6[mental]|shortLabel].</p>"
    },
    "rules": [],
    "slug": "shotalashu-support-benefit",
    "_migration": {
      "version": 0.926,
      "lastMigration": null
    },
    "traits": {
      "otherTags": [],
      "value": []
    },
    "publication": {
      "title": "Pathfinder: Howl of the Wild",
      "authors": "",
      "license": "ORC",
      "remaster": false
    },
    "actionType": {
      "value": "action"
    },
    "category": "offensive",
    "actions": {
      "value": 1
    },
    "deathNote": false
  },
  "_id": "ufAZJqCN7ZOBhMSJ",
  "img": "systems/pf2e/icons/actions/OneAction.webp",
  "folder": null,
  "sort": 2600000,
  "ownership": {
    "default": 0,
    "vawHfUxddL5ZhUl0": 3
  },
  "flags": {
    "scene-packer": {
      "hash": "6fae6910773cf24e2efcb4bd12f59a849d052a61"
    }
  },
  "_stats": {
    "systemId": "pf2e",
    "systemVersion": "6.7.2",
    "coreVersion": "12.331",
    "compendiumSource": null,
    "duplicateSource": null
  },
  "_key": "!items!ufAZJqCN7ZOBhMSJ"
}
