{
  "_id": "uR3j6TAJFeOVUHpY",
  "name": "Lurching Rush",
  "type": "action",
  "img": "systems/pf2e/icons/actions/TwoActions.webp",
  "effects": [],
  "folder": null,
  "sort": 6900000,
  "flags": {
    "core": {}
  },
  "system": {
    "description": {
      "gm": "",
      "value": "<p>The monitor lizard Strides and then makes a jaws Strike. If it moved at least 20 feet away from its starting position, it gains a +2 circumstance bonus to this attack roll.</p>"
    },
    "rules": [],
    "slug": "lurching-rush",
    "_migration": {
      "version": 0.952,
      "previous": {
        "schema": 0.935,
        "foundry": "13.350",
        "system": "7.7.1"
      }
    },
    "traits": {
      "otherTags": [],
      "value": []
    },
    "publication": {
      "title": "Pathfinder #154: Siege of the Dinosaurs",
      "authors": "",
      "license": "OGL",
      "remaster": false
    },
    "actionType": {
      "value": "action"
    },
    "category": "offensive",
    "actions": {
      "value": 2
    },
    "deathNote": false
  },
  "ownership": {
    "default": 0,
    "wT1HOeaOBCFxTCiE": 3
  },
  "_stats": {
    "systemId": "pf2e",
    "systemVersion": "7.7.1",
    "coreVersion": "13.350",
    "compendiumSource": "Compendium.pf2e-animal-companions.AC-Advanced-Maneuvers.Item.uR3j6TAJFeOVUHpY",
    "duplicateSource": null,
    "exportSource": null
  },
  "_key": "!items!uR3j6TAJFeOVUHpY"
}
