{
  "name": "Throw Rock",
  "type": "action",
  "effects": [],
  "system": {
    "_migration": {
      "version": 0.935,
      "previous": null
    },
    "description": {
      "value": "<p>The arboreal sapling Interacts to pick up a rock within reach or retrieve a stowed rock, then throws it with a ranged rock Strike that deals a base of 1d6 bludgeoning damage with a range increment of 30 feet. The damage is 2d6 for a mature arboreal sapling and 3d6 for a specialized one.</p>",
      "gm": ""
    },
    "publication": {
      "title": "Pathfinder Player Core",
      "authors": "",
      "license": "ORC",
      "remaster": true
    },
    "rules": [
      {
        "key": "RollOption",
        "option": "throw-rock",
        "toggleable": true
      },
      {
        "damage": {
          "base": {
            "damageType": "bludgeoning",
            "dice": 1,
            "die": "d6"
          }
        },
        "key": "Strike",
        "label": "Rock",
        "range": {
          "increment": 30
        },
        "predicate": [
          "throw-rock"
        ],
        "img": "icons/commodities/stone/rock-chunk-grey.webp"
      },
      {
        "key": "DamageAlteration",
        "selectors": [
          "{item|id}-damage"
        ],
        "mode": "upgrade",
        "property": "dice-number",
        "value": 2,
        "predicate": [
          "feature:mature-animal-companion"
        ]
      },
      {
        "key": "DamageAlteration",
        "selectors": [
          "{item|id}-damage"
        ],
        "mode": "upgrade",
        "property": "dice-number",
        "value": 3,
        "predicate": [
          "feature:specialized-animal-companion"
        ]
      }
    ],
    "slug": "throw-rock",
    "traits": {
      "otherTags": [],
      "value": []
    },
    "actionType": {
      "value": "action"
    },
    "actions": {
      "value": 1
    },
    "category": "offensive",
    "deathNote": false
  },
  "_id": "tLUBgSE9Mm6ic6sY",
  "img": "systems/pf2e/icons/actions/Reaction.webp",
  "folder": null,
  "sort": 0,
  "ownership": {
    "default": 0,
    "AhhBYTk3xYRMuz4T": 3
  },
  "flags": {},
  "_stats": {
    "compendiumSource": null,
    "duplicateSource": null,
    "coreVersion": "13.350",
    "systemId": "pf2e",
    "systemVersion": "7.6.4",
    "exportSource": null
  },
  "_key": "!items!tLUBgSE9Mm6ic6sY"
}
