{
  "_id": "8z71PBlZBSXkKkLm",
  "name": "Cave Gecko",
  "type": "ancestry",
  "img": "systems/pf2e/icons/default-icons/ancestry.svg",
  "effects": [],
  "folder": null,
  "sort": 1200000,
  "flags": {
    "core": {
      "sourceId": "Compendium.pf2e-animal-companions.AC-Ancestries-and-Class.Item.8z71PBlZBSXkKkLm"
    },
    "exportSource": {
      "world": "ac",
      "system": "pf2e",
      "coreVersion": "0.8.8",
      "systemVersion": "2.6.0.6437"
    }
  },
  "system": {
    "description": {
      "gm": "",
      "value": "<p>Your companion is a sticky-footed lizard like a gecko or anole.</p>\n<p><strong>Size</strong> Small</p>\n<p><strong>Melee</strong> <span class=\"pf2-icon\">a</span> jaws (finesse), <strong>Damage</strong> 1d6 piercing</p>\n<p><strong>Str</strong> +2, <strong>Dex</strong> +3, <strong>Con</strong> +1, <strong>Int</strong> -4, <strong>Wis</strong> +2, <strong>Cha</strong> +0</p>\n<p><strong>Hit Points</strong> 6</p>\n<p><strong>Skill</strong> Stealth</p>\n<p><strong>Senses</strong> low-light vision, scent (imprecise) 30 feet</p>\n<p><strong>Speed</strong> 25 feet, climb 25 feet</p>\n<p><strong>Support Benefit</strong> Your cave gecko helps you stay afoot, leaning into you and propping you up as you maneuver your opponent. Until the end of your next turn, as long as you are adjacent to your cave gecko, if you attempt to Disarm, Shove, or Trip an opponent and roll a critical failure, you get a failure instead.</p>\n<p><strong>Advanced Maneuver</strong> @Compendium[pf2e-animal-companions.AC-Advanced-Maneuvers.q0Vh2V6KlzdMi1Pv]{Tongue Pull}</p>"
    },
    "rules": [
      {
        "key": "ActiveEffectLike",
        "value": 2,
        "mode": "add",
        "path": "system.abilities.str.mod"
      },
      {
        "key": "ActiveEffectLike",
        "value": 3,
        "mode": "add",
        "path": "system.abilities.dex.mod"
      },
      {
        "key": "ActiveEffectLike",
        "value": 1,
        "mode": "add",
        "path": "system.abilities.con.mod"
      },
      {
        "key": "ActiveEffectLike",
        "value": 2,
        "mode": "add",
        "path": "system.abilities.wis.mod"
      },
      {
        "key": "ActiveEffectLike",
        "value": 1,
        "mode": "add",
        "path": "system.skills.ste.rank"
      },
      {
        "key": "BaseSpeed",
        "selector": "climb",
        "value": 25
      },
      {
        "key": "GrantItem",
        "uuid": "Compendium.pf2e-animal-companions.AC-Features.Item.KKOgokqHa7RjVDN6"
      },
      {
        "acuity": "imprecise",
        "key": "Sense",
        "range": 30,
        "selector": "scent"
      },
      {
        "category": "unarmed",
        "damage": {
          "base": {
            "damageType": "piercing",
            "dice": 1,
            "die": "d6"
          }
        },
        "group": "brawling",
        "key": "Strike",
        "label": "PF2E.Weapon.Base.jaws",
        "range": null,
        "traits": [
          "unarmed",
          "finesse"
        ],
        "img": "systems/pf2e/icons/unarmed-attacks/jaws.webp",
        "replaceBasicUnarmed": true
      },
      {
        "key": "RollOption",
        "domain": "all",
        "option": "self:ancestry:cave-gecko",
        "priority": 1
      },
      {
        "key": "GrantItem",
        "uuid": "Compendium.pf2e-animal-companions.AC-Support.Item.nDUwRm0TOtc2EX0O"
      }
    ],
    "slug": "cave-gecko",
    "_migration": {
      "version": null,
      "lastMigration": null
    },
    "traits": {
      "otherTags": [],
      "value": [
        "animal"
      ],
      "rarity": "common"
    },
    "publication": {
      "title": "",
      "authors": "",
      "license": "OGL",
      "remaster": false
    },
    "hp": 6,
    "size": "sm",
    "reach": 5,
    "speed": 25,
    "boosts": {
      "0": {
        "value": []
      },
      "1": {
        "value": []
      },
      "2": {
        "value": [
          "str",
          "dex",
          "con",
          "int",
          "wis",
          "cha"
        ]
      }
    },
    "flaws": {
      "0": {
        "value": []
      }
    },
    "languages": {
      "value": [],
      "custom": ""
    },
    "additionalLanguages": {
      "count": 0,
      "value": [],
      "custom": ""
    },
    "items": {},
    "vision": "lowLightVision",
    "source": {
      "value": "Pathfinder #154: Siege of the Dinosaurs"
    },
    "schema": {
      "version": 0.854,
      "lastMigration": {
        "datetime": "2023-06-27T14:17:44.565-04:00",
        "version": {
          "schema": 0.845,
          "foundry": "11.307",
          "system": "5.3.1"
        }
      }
    },
    "rarity": {
      "value": "common"
    }
  },
  "ownership": {
    "default": 0,
    "rDxs69lNqIFN75Bl": 3
  },
  "_stats": {
    "systemId": "pf2e",
    "systemVersion": "5.15.3",
    "coreVersion": "12.331",
    "compendiumSource": "Compendium.pf2e-animal-companions.AC-Ancestries-and-Class.Item.8z71PBlZBSXkKkLm",
    "duplicateSource": null
  },
  "_key": "!items!8z71PBlZBSXkKkLm"
}
