{
  "name": "Metal Elemental",
  "type": "ancestry",
  "img": "systems/pf2e/icons/default-icons/ancestry.svg",
  "effects": [],
  "flags": {
    "core": {}
  },
  "system": {
    "description": {
      "gm": "",
      "value": "<p>Your companion is a metal elemental, such as a mercurial. Metal elementals don't have any special access because druids don't have an order dedicated to the elemental magic of metal.</p><p><strong>Size</strong> Small</p><p><strong>Melee</strong> <span class=\"pf2-icon\">1</span> spike, <strong>Damage</strong> 1d8 piercing</p><p><strong>Str</strong> +2, <strong>Dex</strong> +1, <strong>Con</strong> +2, <strong>Int</strong> –4, <strong>Wis</strong> +1, <strong>Cha</strong> +0</p><p><strong>Hit Points</strong> 8</p><p><strong>Skill</strong> Intimidation</p><p><strong>Senses</strong> darkvision</p><p><strong>Speed</strong> 25 feet</p><p><strong>Support Benefit</strong> Your metal elemental pierces an enemy with metal spikes that cause it to bleed. Until the start of your next turn, your Strikes that damage a creature in your metal elemental's reach also deal 1d6 persistent bleed damage. If your metal elemental is nimble or savage, the persistent bleed damage increases to 2d6.</p><p><strong>Advanced Maneuver</strong> @UUID[Compendium.pf2e-animal-companions.AC-Advanced-Maneuvers.Item.oyNZpuQ6EU3prvo2]{Spiked Bunker}</p>"
    },
    "rules": [
      {
        "key": "GrantItem",
        "uuid": "Compendium.pf2e-animal-companions.AC-Features.Item.KKOgokqHa7RjVDN6",
        "allowDuplicate": false
      },
      {
        "key": "ActiveEffectLike",
        "value": 2,
        "mode": "add",
        "path": "system.abilities.str.mod"
      },
      {
        "key": "ActiveEffectLike",
        "value": 1,
        "mode": "add",
        "path": "system.abilities.dex.mod"
      },
      {
        "key": "ActiveEffectLike",
        "value": 2,
        "mode": "add",
        "path": "system.abilities.con.mod"
      },
      {
        "key": "ActiveEffectLike",
        "value": -4,
        "mode": "add",
        "path": "system.abilities.int.mod"
      },
      {
        "key": "ActiveEffectLike",
        "value": 1,
        "mode": "add",
        "path": "system.abilities.wis.mod"
      },
      {
        "key": "ActiveEffectLike",
        "value": 1,
        "mode": "add",
        "path": "system.skills.intimidation.rank"
      },
      {
        "category": "unarmed",
        "damage": {
          "base": {
            "damageType": "piercing",
            "dice": 1,
            "die": "d8"
          }
        },
        "group": "brawling",
        "key": "Strike",
        "label": "Spike",
        "range": null,
        "traits": [
          "unarmed"
        ],
        "img": "icons/environment/traps/metal-spikes.webp",
        "replaceBasicUnarmed": true
      },
      {
        "key": "GrantItem",
        "uuid": "Compendium.pf2e-animal-companions.AC-Support.Item.SZD1hU2ageIDw4To"
      },
      {
        "key": "ActiveEffectLike",
        "mode": "override",
        "path": "flags.pf2e.companionCompendia.advancedManeuver",
        "value": "Compendium.pf2e-animal-companions.AC-Advanced-Maneuvers.Item.oyNZpuQ6EU3prvo2"
      }
    ],
    "slug": "metal-elemental",
    "_migration": {
      "version": 0.935,
      "lastMigration": null,
      "previous": {
        "schema": 0.854,
        "foundry": "12.331",
        "system": "6.8.0"
      }
    },
    "traits": {
      "otherTags": [],
      "value": [
        "elemental",
        "metal"
      ],
      "rarity": "uncommon"
    },
    "publication": {
      "title": "Pathfinder Rage of Elements",
      "authors": "",
      "license": "OGL",
      "remaster": true
    },
    "hp": 8,
    "size": "sm",
    "hands": 2,
    "reach": 5,
    "speed": 25,
    "boosts": {
      "0": {
        "value": []
      },
      "1": {
        "value": []
      },
      "2": {
        "value": []
      }
    },
    "flaws": {
      "0": {
        "value": []
      }
    },
    "languages": {
      "value": [],
      "custom": ""
    },
    "additionalLanguages": {
      "count": 0,
      "value": [],
      "custom": ""
    },
    "items": {},
    "vision": "darkvision",
    "voluntaryBoosts": {},
    "voluntaryFlaws": {}
  },
  "_stats": {
    "systemId": "pf2e",
    "systemVersion": "6.8.0",
    "coreVersion": "13.350",
    "compendiumSource": null,
    "duplicateSource": null,
    "exportSource": null
  },
  "_id": "BPo2AA9M7OBqJIYY",
  "folder": "Rn81F1uZdgYGoXoS",
  "sort": 4800000,
  "ownership": {
    "default": 0,
    "qA45GVv5hySaf9b5": 3
  },
  "_key": "!items!BPo2AA9M7OBqJIYY"
}
